Workbook
Name ClienteLista: 'LISTAS + README'!$K$13:$K$15
Name ComplejidadLista: 'LISTAS + README'!$E$13:$E$16
Name EtapasServicio: 'LISTAS + README'!$C$13:$C$17
Name ModeloLista: 'LISTAS + README'!$N$13:$N$17
Name TablaTarifas: 'LISTAS + README'!$A$24:$F$29
Name TiposProyecto: 'LISTAS + README'!$A$13:$A$18
Name UrgenciaLista: 'LISTAS + README'!$H$13:$H$15

Sheet LISTAS + README
A1: CALCULADORA DE HONORARIOS — README
A3: 1. Llena solo las celdas amarillas en la hoja CALCULADORA.
A4: 2. Selecciona Tipo de proyecto, Etapa/Servicio, Complejidad, Urgencia y Tipo de cliente.
A5: 3. Ingresa área, número de reuniones/visitas y opcionales.
A6: 4. La hoja calcula un honorario referencial con ajustes por complejidad, urgencia, cliente y forma de contratación.
A7: 5. Usa PRESENTACION para exportar un resumen limpio a PDF o compartir internamente.
A8: 6. Edita tarifas y multiplicadores en esta misma hoja si quieres adaptar la herramienta a tu mercado.
A9: 7. Esta calculadora es referencial: la decisión final debe validarse con alcance, exclusiones y matriz de entregables.
A12: LISTA_TIPO_PROYECTO | C12: LISTA_ETAPA | E12: LISTA_COMPLEJIDAD | H12: LISTA_URGENCIA | K12: LISTA_CLIENTE | N12: LISTA_MODELO
A13: Vivienda | C13: Levantamiento | E13: Baja | F13: 0.9 | H13: Normal | I13: 1 | K13: Particular | L13: 1 | N13: Suma alzada | O13: 1
A14: Comercial | C14: Anteproyecto | E14: Media | F14: 1 | H14: Rápido | I14: 1.1 | K14: Empresa | L14: 1.08 | N14: Precios unitarios | O14: 1.05
A15: Oficina | C15: Proyecto arquitectónico | E15: Alta | F15: 1.15 | H15: Urgente | I15: 1.2 | K15: Institucional | L15: 1.15 | N15: Cost + Fee | O15: 0.95
A16: Remodelación | C16: Expediente técnico | E16: Muy alta | F16: 1.3 | N16: Gestión de obra | O16: 0.9
A17: Interiorismo | C17: Supervisión | N17: Diseño + Build | O17: 1.12
A18: Industrial pequeño
A22: TARIFAS BASE POR M2 (S/) | H22: OTROS PARÁMETROS
A23: Tipo de proyecto | B23: Levantamiento | C23: Anteproyecto | D23: Proyecto arquitectónico | E23: Expediente técnico | F23: Supervisión | H23: Costo por reunión extra (S/) | I23: 240
A24: Vivienda | B24: 8 | C24: 35 | D24: 55 | E24: 78 | F24: 12 | H24: Costo por visita extra (S/) | I24: 180
A25: Comercial | B25: 10 | C25: 38 | D25: 60 | E25: 85 | F25: 14 | H25: Costo por render extra (S/) | I25: 250
A26: Oficina | B26: 9 | C26: 36 | D26: 58 | E26: 82 | F26: 13 | H26: Buffer comercial mínimo | I26: 0.08
A27: Remodelación | B27: 12 | C27: 42 | D27: 68 | E27: 95 | F27: 16 | H27: IGV | I27: 0.18
A28: Interiorismo | B28: 11 | C28: 40 | D28: 65 | E28: 90 | F28: 15
A29: Industrial pequeño | B29: 8 | C29: 30 | D29: 48 | E29: 70 | F29: 12
H32: HITOS REFERENCIALES
H33: Hito | I33: %
H34: Adelanto | I34: 0.5
H35: Mitad | I35: 0.25
H36: Entrega | I36: 0.25

Sheet CALCULADORA
A1: CALCULADORA DE HONORARIOS
A3: DATOS DEL PROYECTO | F3: FACTORES
A4: Cliente | F4: Complejidad | G4: Muy alta
A5: Proyecto | F5: Urgencia | G5: Urgente
A6: Fecha | B6: =TODAY() -> 46093 | F6: Tipo de cliente | G6: Empresa
A7: Tipo de proyecto | B7: Industrial pequeño | F7: Margen comercial adicional | G7: 0.008
A8: Etapa / servicio | B8: Proyecto arquitectónico | F8: Descuento comercial | G8: 0
A9: Área (m²) | B9: 160 | F9: Redondeo sugerido | G9: 50
A10: Modelo de contratación | B10: Suma alzada
A11: Incluir IGV | B11: Sí
A13: EXTRAS | F13: RESULTADO
A14: Reuniones incluidas | B14: 2 | F14: Tarifa base por m² | G14: =INDEX('LISTAS + README'!$B$24:$F$29,MATCH(B7,'LISTAS + README'!$A$24:$A$29,0),MATCH(B8,'LISTAS + README'!$B$23:$F$23,0)) -> 48
A15: Reuniones extra | B15: 3 | F15: Honorario base | G15: =B9*G14 -> 7680
A16: Visitas incluidas | B16: 1 | F16: Factor complejidad | G16: =VLOOKUP(G4,'LISTAS + README'!$E$13:$F$16,2,FALSE) -> 1.3
A17: Visitas extra | B17: 0 | F17: Factor urgencia | G17: =VLOOKUP(G5,'LISTAS + README'!$H$13:$I$15,2,FALSE) -> 1.2
A18: Renders incluidos | B18: 2 | F18: Factor cliente | G18: =VLOOKUP(G6,'LISTAS + README'!$K$13:$L$15,2,FALSE) -> 1.08
A19: Renders extra | B19: 0 | F19: Factor modelo | G19: =VLOOKUP(B10,'LISTAS + README'!$N$13:$O$17,2,FALSE) -> 1
F20: Honorario ajustado | G20: =G15*G16*G17*G18*G19*(1+G7)*(1-G8) -> 13042.778
F21: Extras | G21: =B15*'LISTAS + README'!$I$23+B17*'LISTAS + README'!$I$24+B19*'LISTAS + README'!$I$25 -> 720
A22: HITOS DE COBRO REFERENCIALES | F22: Subtotal | G22: =G20+G21 -> 13762.778
A23: Hito | B23: % | C23: Monto | D23: Comentario | F23: IGV | G23: =IF(B11="Sí",G22*'LISTAS + README'!$I$27,0) -> 2477.3001
A24: ='LISTAS + README'!H34 -> Adelanto | B24: ='LISTAS + README'!I34 -> 0.5 | C24: =$G$24*B24 -> 8125 | D24: Pago referencial | F24: Total sugerido | G24: =MROUND(G22+G23,G9) -> 16250
A25: ='LISTAS + README'!H35 -> Mitad | B25: ='LISTAS + README'!I35 -> 0.25 | C25: =$G$24*B25 -> 4062.5 | D25: Pago referencial | F25: Rango sugerido | G25: ="S/ "&TEXT(G24*(1-'LISTAS + README'!$I$26),"#,##0")&" a S/ "&TEXT(G24*(1+'LISTAS + README'!$I$26),"#,##0") -> S/ 14,950 a S/ 17,550
A26: ='LISTAS + README'!H36 -> Entrega | B26: ='LISTAS + README'!I36 -> 0.25 | C26: =$G$24*B26 -> 4062.5 | D26: Pago referencial
A38: Notas
A39: La calculadora es una referencia comercial. Ajusta alcance, exclusiones, cronograma y condiciones antes de enviar una cotización final.

Sheet PRESENTACION
A1: RESUMEN DE HONORARIOS
A3: Cliente | B3: =IF(CALCULADORA!B4="","",CALCULADORA!B4) | D3: Honorario | E3: =CALCULADORA!G24 -> 16250
A4: Proyecto | B4: =IF(CALCULADORA!B5="","",CALCULADORA!B5)
A5: Fecha | B5: =CALCULADORA!B6 -> 46093 | D5: Tarifa base | E5: =CALCULADORA!G14 -> 48
A6: Tipo de proyecto | B6: =CALCULADORA!B7 -> Industrial pequeño | D6: Complejidad | E6: =CALCULADORA!G4 -> Muy alta
A7: Etapa / servicio | B7: =CALCULADORA!B8 -> Proyecto arquitectónico | D7: Urgencia | E7: =CALCULADORA!G5 -> Urgente
A8: Modelo de contratación | B8: =CALCULADORA!B10 -> Suma alzada
A9: Área | B9: =CALCULADORA!B9&" m²" -> 160 m²
A11: DESGLOSE
A12: Concepto | E12: Monto | F12: Notas
A13: Honorario base | E13: =CALCULADORA!G15 -> 7680 | F13: Área × tarifa base
A14: Ajustes | E14: =CALCULADORA!G20-CALCULADORA!G15 -> 5362.7781 | F14: Complejidad, urgencia, cliente y modelo
A15: Extras | E15: =CALCULADORA!G21 -> 720 | F15: Reuniones, visitas y renders extra
A16: IGV | E16: =CALCULADORA!G23 -> 2477.3001 | F16: Si corresponde
A17: TOTAL | E17: =CALCULADORA!G24 -> 16250 | F17: Monto Total
A20: HITOS DE COBRO REFERENCIALES
A21: Hito | B21: % | C21: Monto
A22: =CALCULADORA!A24 -> Adelanto | B22: =CALCULADORA!B24 -> 0.5 | C22: =CALCULADORA!C24 -> 8125
A23: =CALCULADORA!A25 -> Mitad | B23: =CALCULADORA!B25 -> 0.25 | C23: =CALCULADORA!C25 -> 4062.5
A24: =CALCULADORA!A26 -> Entrega | B24: =CALCULADORA!B26 -> 0.25 | C24: =CALCULADORA!C26 -> 4062.5
A27: Notas
A28: Resumen referencial para convertir en cotización final. Validar alcance, entregables, exclusiones, cronograma y condiciones antes de enviarlo al cliente.
