Workbook
Name lstEstadosAdic: 'LISTAS + README'!$A$56:$A$59
Name lstEstadosVal: 'LISTAS + README'!$A$11:$A$15
Name lstMonedas: 'LISTAS + README'!$A$51:$A$52
Name lstPeriodicidad: 'LISTAS + README'!$A$37:$A$39
Name lstResponsables: 'LISTAS + README'!$A$43:$A$47
Name lstTiposItem: 'LISTAS + README'!$A$29:$A$33
Name lstUnidades: 'LISTAS + README'!$A$19:$A$25

Sheet LISTAS + README
A1: Plantilla de Valorización de Avance de Obra
A3: README
A4: Objetivo | B4: Registrar el presupuesto base, valorizar el avance de un período, controlar adicionales y pagos, y emitir una hoja de presentación.
A5: Flujo de uso | B5: 1) Llene DATOS GENERALES. 2) Cargue PRESUPUESTO BASE. 3) Registre avances en VALORIZACIÓN. 4) Registre ADICIONALES / DEDUCTIVOS. 5) Actualice CONTROL DE PAGOS. 6) Revise RESUMEN y PRESENTACIÓN.
A6: Convención | B6: Entradas editables en amarillo. Fórmulas en negro. Celdas enlazadas entre hojas en verde.
A10: Estados valorización
A11: Borrador
A12: Revisado
A13: Aprobado
A14: Observado
A15: Pagado
A18: Unidades
A19: und
A20: m²
A21: m³
A22: ml
A23: gl
... A59: Observado

Sheet DATOS GENERALES
A1: DATOS GENERALES
A3: Cliente | B3: Cliente ejemplo SAC
A4: Proyecto | B4: Remodelación Oficinas Piso 3
A5: Código | B5: VAL-001
A6: Ubicación | B6: Lima, Perú
A7: Contratista / Proveedor | B7: Contratista Ejemplo SRL
A8: Supervisor / Responsable | B8: Arq. Responsable
A9: Moneda | B9: S/.
A10: Monto contratado | B10: 150000
A11: Periodicidad de valorización | B11: Mes
A12: N.° de valorización | B12: 1
A13: Periodo valorizado | B13: Mes 1
A14: Fecha de corte | B14: 2026-03-16
A15: Fecha de emisión | B15: 2026-03-20
A16: Fecha de inicio contractual | B16: 2026-03-21
A17: Plazo contractual (días) | B17: 90
A18: Estado de valorización | B18: Borrador
A19: Observaciones generales | B19: Plantilla base editable.

Sheet PRESUPUESTO BASE
A1: PRESUPUESTO BASE
A3: Ítem | B3: Código | C3: Tipo de ítem | D3: Partida | E3: Unidad | F3: Metrado contratado | G3: Precio unitario | H3: Subtotal contratado | I3: Peso % | J3: Responsable | K3: Observaciones
A4: 1 | B4: ARQ-01 | C4: Partida | D4: Demoliciones menores | E4: m² | F4: 120 | G4: 25 | H4: =F4*G4 -> 3000 | I4: =IFERROR(H4/SUM($H$4:$H$103),0) -> 0.022641509 | J4: Contratista
A5: 2 | B5: ARQ-02 | C5: Partida | D5: Tabiquería drywall | E5: m² | F5: 180 | G5: 95 | H5: =F5*G5 -> 17100 | I5: =IFERROR(H5/SUM($H$4:$H$103),0) -> 0.1290566 | J5: Contratista
A6: 3 | B6: ARQ-03 | C6: Partida | D6: Cielorraso | E6: m² | F6: 180 | G6: 62 | H6: =F6*G6 -> 11160 | I6: =IFERROR(H6/SUM($H$4:$H$103),0) -> 0.084226415 | J6: Contratista
A7: 4 | B7: ARQ-04 | C7: Partida | D7: Piso porcelanato | E7: m² | F7: 220 | G7: 118 | H7: =F7*G7 -> 25960 | I7: =IFERROR(H7/SUM($H$4:$H$103),0) -> 0.19592453 | J7: Contratista
A8: 5 | B8: ARQ-05 | C8: Partida | D8: Pintura general | E8: m² | F8: 850 | G8: 16 | H8: =F8*G8 -> 13600 | I8: =IFERROR(H8/SUM($H$4:$H$103),0) -> 0.10264151 | J8: Contratista
A9: 6 | B9: ELE-01 | C9: Partida | D9: Red eléctrica | E9: gl | F9: 1 | G9: 18500 | H9: =F9*G9 -> 18500 | I9: =IFERROR(H9/SUM($H$4:$H$103),0) -> 0.13962264 | J9: Contratista
A10: 7 | B10: SAN-01 | C10: Partida | D10: Adecuación sanitaria | E10: gl | F10: 1 | G10: 9200 | H10: =F10*G10 -> 9200 | I10: =IFERROR(H10/SUM($H$4:$H$103),0) -> 0.069433962 | J10: Contratista
A11: 8 | B11: MOB-01 | C11: Partida | D11: Carpintería fija | E11: gl | F11: 1 | G11: 14800 | H11: =F11*G11 -> 14800 | I11: =IFERROR(H11/SUM($H$4:$H$103),0) -> 0.11169811 | J11: Contratista
A12: 9 | B12: VID-01 | C12: Partida | D12: Mamparas y vidrio | E12: m² | F12: 42 | G12: 390 | H12: =F12*G12 -> 16380 | I12: =IFERROR(H12/SUM($H$4:$H$103),0) -> 0.12362264 | J12: Contratista
A13: 10 | B13: FIN-01 | C13: Partida | D13: Limpieza y cierre | E13: gl | F13: 1 | G13: 2800 | H13: =F13*G13 -> 2800 | I13: =IFERROR(H13/SUM($H$4:$H$103),0) -> 0.021132075 | J13: Contratista
H14: =F14*G14 -> 0 | I14: =IFERROR(H14/SUM($H$4:$H$103),0) -> 0
H15: =F15*G15 -> 0 | I15: =IFERROR(H15/SUM($H$4:$H$103),0) -> 0
H16: =F16*G16 -> 0 | I16: =IFERROR(H16/SUM($H$4:$H$103),0) -> 0
H17: =F17*G17 -> 0 | I17: =IFERROR(H17/SUM($H$4:$H$103),0) -> 0
H18: =F18*G18 -> 0 | I18: =IFERROR(H18/SUM($H$4:$H$103),0) -> 0
H19: =F19*G19 -> 0 | I19: =IFERROR(H19/SUM($H$4:$H$103),0) -> 0
H20: =F20*G20 -> 0 | I20: =IFERROR(H20/SUM($H$4:$H$103),0) -> 0
H21: =F21*G21 -> 0 | I21: =IFERROR(H21/SUM($H$4:$H$103),0) -> 0
H22: =F22*G22 -> 0 | I22: =IFERROR(H22/SUM($H$4:$H$103),0) -> 0
H23: =F23*G23 -> 0 | I23: =IFERROR(H23/SUM($H$4:$H$103),0) -> 0
H24: =F24*G24 -> 0 | I24: =IFERROR(H24/SUM($H$4:$H$103),0) -> 0
H25: =F25*G25 -> 0 | I25: =IFERROR(H25/SUM($H$4:$H$103),0) -> 0
... H103: =F103*G103 -> 0 | I103: =IFERROR(H103/SUM($H$4:$H$103),0) -> 0
G105: Total | H105: =SUM(H4:H103) -> 132500

Sheet VALORIZACIÓN
A1: VALORIZACIÓN DEL PERÍODO
A3: Ítem | B3: Código | C3: Partida | D3: Unidad | E3: Metrado contratado | F3: Precio unitario | G3: Monto contratado | H3: Avance anterior % | I3: Avance del período % | J3: Avance acumulado % | K3: Metrado ejecutado del período | L3: Metrado ejecutado acumulado | M3: Monto valorizado anterior | N3: Monto valorizado del período | O3: Monto valorizado acumulado | P3: Saldo por ejecutar | Q3: Estado | R3: Observaciones | S3: Movimiento idx
A4: ='PRESUPUESTO BASE'!A4 -> 1 | B4: ='PRESUPUESTO BASE'!B4 -> ARQ-01 | C4: ='PRESUPUESTO BASE'!D4 -> Demoliciones menores | D4: ='PRESUPUESTO BASE'!E4 -> m² | E4: ='PRESUPUESTO BASE'!F4 -> 120 | F4: ='PRESUPUESTO BASE'!G4 -> 25 | G4: ='PRESUPUESTO BASE'!H4 -> 3000 | H4: 0.2 | I4: 0.15 | J4: =MIN(1,H4+I4) -> 0.35 | K4: =E4*I4 -> 18 | L4: =E4*J4 -> 42 | M4: =G4*H4 -> 600 | N4: =G4*I4 -> 450 | O4: =G4*J4 -> 1050 | P4: =G4-O4 -> 1950 | Q4: Revisado | S4: =IF(N4>0,COUNTIF($N$4:N4,">0"),"") -> 1
A5: ='PRESUPUESTO BASE'!A5 -> 2 | B5: ='PRESUPUESTO BASE'!B5 -> ARQ-02 | C5: ='PRESUPUESTO BASE'!D5 -> Tabiquería drywall | D5: ='PRESUPUESTO BASE'!E5 -> m² | E5: ='PRESUPUESTO BASE'!F5 -> 180 | F5: ='PRESUPUESTO BASE'!G5 -> 95 | G5: ='PRESUPUESTO BASE'!H5 -> 17100 | H5: 0.1 | I5: 0.2 | J5: =MIN(1,H5+I5) -> 0.3 | K5: =E5*I5 -> 36 | L5: =E5*J5 -> 54 | M5: =G5*H5 -> 1710 | N5: =G5*I5 -> 3420 | O5: =G5*J5 -> 5130 | P5: =G5-O5 -> 11970 | Q5: Revisado | S5: =IF(N5>0,COUNTIF($N$4:N5,">0"),"") -> 2
A6: ='PRESUPUESTO BASE'!A6 -> 3 | B6: ='PRESUPUESTO BASE'!B6 -> ARQ-03 | C6: ='PRESUPUESTO BASE'!D6 -> Cielorraso | D6: ='PRESUPUESTO BASE'!E6 -> m² | E6: ='PRESUPUESTO BASE'!F6 -> 180 | F6: ='PRESUPUESTO BASE'!G6 -> 62 | G6: ='PRESUPUESTO BASE'!H6 -> 11160 | H6: 0 | I6: 0.1 | J6: =MIN(1,H6+I6) -> 0.1 | K6: =E6*I6 -> 18 | L6: =E6*J6 -> 18 | M6: =G6*H6 -> 0 | N6: =G6*I6 -> 1116 | O6: =G6*J6 -> 1116 | P6: =G6-O6 -> 10044 | Q6: Revisado | S6: =IF(N6>0,COUNTIF($N$4:N6,">0"),"") -> 3
A7: ='PRESUPUESTO BASE'!A7 -> 4 | B7: ='PRESUPUESTO BASE'!B7 -> ARQ-04 | C7: ='PRESUPUESTO BASE'!D7 -> Piso porcelanato | D7: ='PRESUPUESTO BASE'!E7 -> m² | E7: ='PRESUPUESTO BASE'!F7 -> 220 | F7: ='PRESUPUESTO BASE'!G7 -> 118 | G7: ='PRESUPUESTO BASE'!H7 -> 25960 | H7: 0.15 | I7: 0.15 | J7: =MIN(1,H7+I7) -> 0.3 | K7: =E7*I7 -> 33 | L7: =E7*J7 -> 66 | M7: =G7*H7 -> 3894 | N7: =G7*I7 -> 3894 | O7: =G7*J7 -> 7788 | P7: =G7-O7 -> 18172 | Q7: Revisado | S7: =IF(N7>0,COUNTIF($N$4:N7,">0"),"") -> 4
A8: ='PRESUPUESTO BASE'!A8 -> 5 | B8: ='PRESUPUESTO BASE'!B8 -> ARQ-05 | C8: ='PRESUPUESTO BASE'!D8 -> Pintura general | D8: ='PRESUPUESTO BASE'!E8 -> m² | E8: ='PRESUPUESTO BASE'!F8 -> 850 | F8: ='PRESUPUESTO BASE'!G8 -> 16 | G8: ='PRESUPUESTO BASE'!H8 -> 13600 | H8: 0 | I8: 0.3 | J8: =MIN(1,H8+I8) -> 0.3 | K8: =E8*I8 -> 255 | L8: =E8*J8 -> 255 | M8: =G8*H8 -> 0 | N8: =G8*I8 -> 4080 | O8: =G8*J8 -> 4080 | P8: =G8-O8 -> 9520 | Q8: Revisado | S8: =IF(N8>0,COUNTIF($N$4:N8,">0"),"") -> 5
A9: ='PRESUPUESTO BASE'!A9 -> 6 | B9: ='PRESUPUESTO BASE'!B9 -> ELE-01 | C9: ='PRESUPUESTO BASE'!D9 -> Red eléctrica | D9: ='PRESUPUESTO BASE'!E9 -> gl | E9: ='PRESUPUESTO BASE'!F9 -> 1 | F9: ='PRESUPUESTO BASE'!G9 -> 18500 | G9: ='PRESUPUESTO BASE'!H9 -> 18500 | H9: 0.25 | I9: 0.15 | J9: =MIN(1,H9+I9) -> 0.4 | K9: =E9*I9 -> 0.15 | L9: =E9*J9 -> 0.4 | M9: =G9*H9 -> 4625 | N9: =G9*I9 -> 2775 | O9: =G9*J9 -> 7400 | P9: =G9-O9 -> 11100 | Q9: Revisado | S9: =IF(N9>0,COUNTIF($N$4:N9,">0"),"") -> 6
A10: ='PRESUPUESTO BASE'!A10 -> 7 | B10: ='PRESUPUESTO BASE'!B10 -> SAN-01 | C10: ='PRESUPUESTO BASE'!D10 -> Adecuación sanitaria | D10: ='PRESUPUESTO BASE'!E10 -> gl | E10: ='PRESUPUESTO BASE'!F10 -> 1 | F10: ='PRESUPUESTO BASE'!G10 -> 9200 | G10: ='PRESUPUESTO BASE'!H10 -> 9200 | H10: 0 | I10: 0.2 | J10: =MIN(1,H10+I10) -> 0.2 | K10: =E10*I10 -> 0.2 | L10: =E10*J10 -> 0.2 | M10: =G10*H10 -> 0 | N10: =G10*I10 -> 1840 | O10: =G10*J10 -> 1840 | P10: =G10-O10 -> 7360 | Q10: Revisado | S10: =IF(N10>0,COUNTIF($N$4:N10,">0"),"") -> 7
A11: ='PRESUPUESTO BASE'!A11 -> 8 | B11: ='PRESUPUESTO BASE'!B11 -> MOB-01 | C11: ='PRESUPUESTO BASE'!D11 -> Carpintería fija | D11: ='PRESUPUESTO BASE'!E11 -> gl | E11: ='PRESUPUESTO BASE'!F11 -> 1 | F11: ='PRESUPUESTO BASE'!G11 -> 14800 | G11: ='PRESUPUESTO BASE'!H11 -> 14800 | H11: 0.1 | I11: 0.05 | J11: =MIN(1,H11+I11) -> 0.15 | K11: =E11*I11 -> 0.05 | L11: =E11*J11 -> 0.15 | M11: =G11*H11 -> 1480 | N11: =G11*I11 -> 740 | O11: =G11*J11 -> 2220 | P11: =G11-O11 -> 12580 | Q11: Revisado | S11: =IF(N11>0,COUNTIF($N$4:N11,">0"),"") -> 8
A12: ='PRESUPUESTO BASE'!A12 -> 9 | B12: ='PRESUPUESTO BASE'!B12 -> VID-01 | C12: ='PRESUPUESTO BASE'!D12 -> Mamparas y vidrio | D12: ='PRESUPUESTO BASE'!E12 -> m² | E12: ='PRESUPUESTO BASE'!F12 -> 42 | F12: ='PRESUPUESTO BASE'!G12 -> 390 | G12: ='PRESUPUESTO BASE'!H12 -> 16380 | H12: 0 | I12: 0.25 | J12: =MIN(1,H12+I12) -> 0.25 | K12: =E12*I12 -> 10.5 | L12: =E12*J12 -> 10.5 | M12: =G12*H12 -> 0 | N12: =G12*I12 -> 4095 | O12: =G12*J12 -> 4095 | P12: =G12-O12 -> 12285 | Q12: Revisado | S12: =IF(N12>0,COUNTIF($N$4:N12,">0"),"") -> 9
A13: ='PRESUPUESTO BASE'!A13 -> 10 | B13: ='PRESUPUESTO BASE'!B13 -> FIN-01 | C13: ='PRESUPUESTO BASE'!D13 -> Limpieza y cierre | D13: ='PRESUPUESTO BASE'!E13 -> gl | E13: ='PRESUPUESTO BASE'!F13 -> 1 | F13: ='PRESUPUESTO BASE'!G13 -> 2800 | G13: ='PRESUPUESTO BASE'!H13 -> 2800 | H13: 0 | I13: 0.4 | J13: =MIN(1,H13+I13) -> 0.4 | K13: =E13*I13 -> 0.4 | L13: =E13*J13 -> 0.4 | M13: =G13*H13 -> 0 | N13: =G13*I13 -> 1120 | O13: =G13*J13 -> 1120 | P13: =G13-O13 -> 1680 | Q13: Revisado | S13: =IF(N13>0,COUNTIF($N$4:N13,">0"),"") -> 10
A14: ='PRESUPUESTO BASE'!A14 -> 0 | B14: ='PRESUPUESTO BASE'!B14 -> 0 | C14: ='PRESUPUESTO BASE'!D14 -> 0 | D14: ='PRESUPUESTO BASE'!E14 -> 0 | E14: ='PRESUPUESTO BASE'!F14 -> 0 | F14: ='PRESUPUESTO BASE'!G14 -> 0 | G14: ='PRESUPUESTO BASE'!H14 -> 0 | J14: =MIN(1,H14+I14) -> 0 | K14: =E14*I14 -> 0 | L14: =E14*J14 -> 0 | M14: =G14*H14 -> 0 | N14: =G14*I14 -> 0 | O14: =G14*J14 -> 0 | P14: =G14-O14 -> 0 | S14: =IF(N14>0,COUNTIF($N$4:N14,">0"),"")
A15: ='PRESUPUESTO BASE'!A15 -> 0 | B15: ='PRESUPUESTO BASE'!B15 -> 0 | C15: ='PRESUPUESTO BASE'!D15 -> 0 | D15: ='PRESUPUESTO BASE'!E15 -> 0 | E15: ='PRESUPUESTO BASE'!F15 -> 0 | F15: ='PRESUPUESTO BASE'!G15 -> 0 | G15: ='PRESUPUESTO BASE'!H15 -> 0 | J15: =MIN(1,H15+I15) -> 0 | K15: =E15*I15 -> 0 | L15: =E15*J15 -> 0 | M15: =G15*H15 -> 0 | N15: =G15*I15 -> 0 | O15: =G15*J15 -> 0 | P15: =G15-O15 -> 0 | S15: =IF(N15>0,COUNTIF($N$4:N15,">0"),"")
A16: ='PRESUPUESTO BASE'!A16 -> 0 | B16: ='PRESUPUESTO BASE'!B16 -> 0 | C16: ='PRESUPUESTO BASE'!D16 -> 0 | D16: ='PRESUPUESTO BASE'!E16 -> 0 | E16: ='PRESUPUESTO BASE'!F16 -> 0 | F16: ='PRESUPUESTO BASE'!G16 -> 0 | G16: ='PRESUPUESTO BASE'!H16 -> 0 | J16: =MIN(1,H16+I16) -> 0 | K16: =E16*I16 -> 0 | L16: =E16*J16 -> 0 | M16: =G16*H16 -> 0 | N16: =G16*I16 -> 0 | O16: =G16*J16 -> 0 | P16: =G16-O16 -> 0 | S16: =IF(N16>0,COUNTIF($N$4:N16,">0"),"")
A17: ='PRESUPUESTO BASE'!A17 -> 0 | B17: ='PRESUPUESTO BASE'!B17 -> 0 | C17: ='PRESUPUESTO BASE'!D17 -> 0 | D17: ='PRESUPUESTO BASE'!E17 -> 0 | E17: ='PRESUPUESTO BASE'!F17 -> 0 | F17: ='PRESUPUESTO BASE'!G17 -> 0 | G17: ='PRESUPUESTO BASE'!H17 -> 0 | J17: =MIN(1,H17+I17) -> 0 | K17: =E17*I17 -> 0 | L17: =E17*J17 -> 0 | M17: =G17*H17 -> 0 | N17: =G17*I17 -> 0 | O17: =G17*J17 -> 0 | P17: =G17-O17 -> 0 | S17: =IF(N17>0,COUNTIF($N$4:N17,">0"),"")
A18: ='PRESUPUESTO BASE'!A18 -> 0 | B18: ='PRESUPUESTO BASE'!B18 -> 0 | C18: ='PRESUPUESTO BASE'!D18 -> 0 | D18: ='PRESUPUESTO BASE'!E18 -> 0 | E18: ='PRESUPUESTO BASE'!F18 -> 0 | F18: ='PRESUPUESTO BASE'!G18 -> 0 | G18: ='PRESUPUESTO BASE'!H18 -> 0 | J18: =MIN(1,H18+I18) -> 0 | K18: =E18*I18 -> 0 | L18: =E18*J18 -> 0 | M18: =G18*H18 -> 0 | N18: =G18*I18 -> 0 | O18: =G18*J18 -> 0 | P18: =G18-O18 -> 0 | S18: =IF(N18>0,COUNTIF($N$4:N18,">0"),"")
A19: ='PRESUPUESTO BASE'!A19 -> 0 | B19: ='PRESUPUESTO BASE'!B19 -> 0 | C19: ='PRESUPUESTO BASE'!D19 -> 0 | D19: ='PRESUPUESTO BASE'!E19 -> 0 | E19: ='PRESUPUESTO BASE'!F19 -> 0 | F19: ='PRESUPUESTO BASE'!G19 -> 0 | G19: ='PRESUPUESTO BASE'!H19 -> 0 | J19: =MIN(1,H19+I19) -> 0 | K19: =E19*I19 -> 0 | L19: =E19*J19 -> 0 | M19: =G19*H19 -> 0 | N19: =G19*I19 -> 0 | O19: =G19*J19 -> 0 | P19: =G19-O19 -> 0 | S19: =IF(N19>0,COUNTIF($N$4:N19,">0"),"")
A20: ='PRESUPUESTO BASE'!A20 -> 0 | B20: ='PRESUPUESTO BASE'!B20 -> 0 | C20: ='PRESUPUESTO BASE'!D20 -> 0 | D20: ='PRESUPUESTO BASE'!E20 -> 0 | E20: ='PRESUPUESTO BASE'!F20 -> 0 | F20: ='PRESUPUESTO BASE'!G20 -> 0 | G20: ='PRESUPUESTO BASE'!H20 -> 0 | J20: =MIN(1,H20+I20) -> 0 | K20: =E20*I20 -> 0 | L20: =E20*J20 -> 0 | M20: =G20*H20 -> 0 | N20: =G20*I20 -> 0 | O20: =G20*J20 -> 0 | P20: =G20-O20 -> 0 | S20: =IF(N20>0,COUNTIF($N$4:N20,">0"),"")
A21: ='PRESUPUESTO BASE'!A21 -> 0 | B21: ='PRESUPUESTO BASE'!B21 -> 0 | C21: ='PRESUPUESTO BASE'!D21 -> 0 | D21: ='PRESUPUESTO BASE'!E21 -> 0 | E21: ='PRESUPUESTO BASE'!F21 -> 0 | F21: ='PRESUPUESTO BASE'!G21 -> 0 | G21: ='PRESUPUESTO BASE'!H21 -> 0 | J21: =MIN(1,H21+I21) -> 0 | K21: =E21*I21 -> 0 | L21: =E21*J21 -> 0 | M21: =G21*H21 -> 0 | N21: =G21*I21 -> 0 | O21: =G21*J21 -> 0 | P21: =G21-O21 -> 0 | S21: =IF(N21>0,COUNTIF($N$4:N21,">0"),"")
A22: ='PRESUPUESTO BASE'!A22 -> 0 | B22: ='PRESUPUESTO BASE'!B22 -> 0 | C22: ='PRESUPUESTO BASE'!D22 -> 0 | D22: ='PRESUPUESTO BASE'!E22 -> 0 | E22: ='PRESUPUESTO BASE'!F22 -> 0 | F22: ='PRESUPUESTO BASE'!G22 -> 0 | G22: ='PRESUPUESTO BASE'!H22 -> 0 | J22: =MIN(1,H22+I22) -> 0 | K22: =E22*I22 -> 0 | L22: =E22*J22 -> 0 | M22: =G22*H22 -> 0 | N22: =G22*I22 -> 0 | O22: =G22*J22 -> 0 | P22: =G22-O22 -> 0 | S22: =IF(N22>0,COUNTIF($N$4:N22,">0"),"")
A23: ='PRESUPUESTO BASE'!A23 -> 0 | B23: ='PRESUPUESTO BASE'!B23 -> 0 | C23: ='PRESUPUESTO BASE'!D23 -> 0 | D23: ='PRESUPUESTO BASE'!E23 -> 0 | E23: ='PRESUPUESTO BASE'!F23 -> 0 | F23: ='PRESUPUESTO BASE'!G23 -> 0 | G23: ='PRESUPUESTO BASE'!H23 -> 0 | J23: =MIN(1,H23+I23) -> 0 | K23: =E23*I23 -> 0 | L23: =E23*J23 -> 0 | M23: =G23*H23 -> 0 | N23: =G23*I23 -> 0 | O23: =G23*J23 -> 0 | P23: =G23-O23 -> 0 | S23: =IF(N23>0,COUNTIF($N$4:N23,">0"),"")
A24: ='PRESUPUESTO BASE'!A24 -> 0 | B24: ='PRESUPUESTO BASE'!B24 -> 0 | C24: ='PRESUPUESTO BASE'!D24 -> 0 | D24: ='PRESUPUESTO BASE'!E24 -> 0 | E24: ='PRESUPUESTO BASE'!F24 -> 0 | F24: ='PRESUPUESTO BASE'!G24 -> 0 | G24: ='PRESUPUESTO BASE'!H24 -> 0 | J24: =MIN(1,H24+I24) -> 0 | K24: =E24*I24 -> 0 | L24: =E24*J24 -> 0 | M24: =G24*H24 -> 0 | N24: =G24*I24 -> 0 | O24: =G24*J24 -> 0 | P24: =G24-O24 -> 0 | S24: =IF(N24>0,COUNTIF($N$4:N24,">0"),"")
A25: ='PRESUPUESTO BASE'!A25 -> 0 | B25: ='PRESUPUESTO BASE'!B25 -> 0 | C25: ='PRESUPUESTO BASE'!D25 -> 0 | D25: ='PRESUPUESTO BASE'!E25 -> 0 | E25: ='PRESUPUESTO BASE'!F25 -> 0 | F25: ='PRESUPUESTO BASE'!G25 -> 0 | G25: ='PRESUPUESTO BASE'!H25 -> 0 | J25: =MIN(1,H25+I25) -> 0 | K25: =E25*I25 -> 0 | L25: =E25*J25 -> 0 | M25: =G25*H25 -> 0 | N25: =G25*I25 -> 0 | O25: =G25*J25 -> 0 | P25: =G25-O25 -> 0 | S25: =IF(N25>0,COUNTIF($N$4:N25,">0"),"")
... A103: ='PRESUPUESTO BASE'!A103 -> 0 | B103: ='PRESUPUESTO BASE'!B103 -> 0 | C103: ='PRESUPUESTO BASE'!D103 -> 0 | D103: ='PRESUPUESTO BASE'!E103 -> 0 | E103: ='PRESUPUESTO BASE'!F103 -> 0 | F103: ='PRESUPUESTO BASE'!G103 -> 0 | G103: ='PRESUPUESTO BASE'!H103 -> 0 | J103: =MIN(1,H103+I103) -> 0 | K103: =E103*I103 -> 0 | L103: =E103*J103 -> 0 | M103: =G103*H103 -> 0 | N103: =G103*I103 -> 0 | O103: =G103*J103 -> 0 | P103: =G103-O103 -> 0 | S103: =IF(N103>0,COUNTIF($N$4:N103,">0"),"")
N105: =SUM(N4:N103) -> 23530 | O105: =SUM(O4:O103) -> 35839 | P105: =SUM(P4:P103) -> 96661

Sheet ADICIONALES
A1: ADICIONALES / DEDUCTIVOS
A3: Ítem | B3: Código | C3: Tipo | D3: Descripción | E3: Sustento / referencia | F3: Unidad | G3: Cantidad | H3: Precio unitario | I3: Monto | J3: Estado | K3: Fecha | L3: Observaciones
A4: 1 | B4: ADC-01 | C4: Adicional | D4: Refuerzo de cableado | E4: RFI-04 | F4: gl | G4: 1 | H4: 3200 | I4: =G4*H4 -> 3200 | J4: Aprobado | K4: 2026-03-24
A5: 2 | B5: DED-01 | C5: Deductivo | D5: Reducción de tabique | E5: OC-02 | F5: m² | G5: 12 | H5: 95 | I5: =G5*H5 -> 1140 | J5: Aprobado | K5: 2026-03-26
I6: =G6*H6 -> 0
I7: =G7*H7 -> 0
I8: =G8*H8 -> 0
I9: =G9*H9 -> 0
I10: =G10*H10 -> 0
I11: =G11*H11 -> 0
I12: =G12*H12 -> 0
I13: =G13*H13 -> 0
I14: =G14*H14 -> 0
I15: =G15*H15 -> 0
I16: =G16*H16 -> 0
I17: =G17*H17 -> 0
... I103: =G103*H103 -> 0

Sheet CONTROL DE PAGOS
A1: CONTROL DE PAGOS
A3: N.° valorización | B3: Periodo | C3: Fecha de emisión | D3: Monto presentado | E3: Monto aprobado | F3: Fecha de aprobación | G3: Fecha de pago | H3: Monto pagado | I3: Saldo por pagar | J3: Estado | K3: Observaciones
A4: 1 | B4: Mes 1 | C4: 2026-03-31 | D4: =RESUMEN!B5 -> 23530 | E4: =D4 -> 23530 | F4: 2026-04-05 | G4: 2026-04-12 | H4: =E4 -> 23530 | I4: =E4-H4 -> 0 | J4: Pagado
I5: =E5-H5 -> 0
I6: =E6-H6 -> 0
I7: =E7-H7 -> 0
I8: =E8-H8 -> 0
I9: =E9-H9 -> 0
I10: =E10-H10 -> 0
I11: =E11-H11 -> 0
I12: =E12-H12 -> 0
I13: =E13-H13 -> 0
I14: =E14-H14 -> 0
I15: =E15-H15 -> 0
I16: =E16-H16 -> 0
... I53: =E53-H53 -> 0

Sheet RESUMEN
A1: RESUMEN DE VALORIZACIÓN
A3: KPIs | E3: Partidas con movimiento en el período
A4: Monto contratado | B4: =SUM('PRESUPUESTO BASE'!H4:H103) -> 132500 | E4: Código | F4: Partida | G4: Val. período | H4: Avance período % | I4: Val. acumulado | J4: Saldo | K4: Saldo
A5: Valorizado del período | B5: =SUM(VALORIZACIÓN!N4:N103) -> 23530 | E5: =IFERROR(INDEX(VALORIZACIÓN!$B$4:$B$103,MATCH(ROWS($E$5:E5),VALORIZACIÓN!$S$4:$S$103,0)),"") -> ARQ-01 | F5: =IFERROR(INDEX(VALORIZACIÓN!$C$4:$C$103,MATCH(ROWS($E$5:E5),VALORIZACIÓN!$S$4:$S$103,0)),"") -> Demoliciones menores | G5: =IF(E5="","",INDEX(VALORIZACIÓN!$N$4:$N$103,MATCH(ROWS($E$5:E5),VALORIZACIÓN!$S$4:$S$103,0))) -> 450 | H5: =IF(E5="","",INDEX(VALORIZACIÓN!$J$4:$J$103,MATCH(ROWS($E$5:E5),VALORIZACIÓN!$S$4:$S$103,0))) -> 0.35 | I5: =IF(E5="","",INDEX(VALORIZACIÓN!$O$4:$O$103,MATCH(ROWS($E$5:E5),VALORIZACIÓN!$S$4:$S$103,0))) -> 1050 | J5: =IF(E5="","",INDEX(VALORIZACIÓN!$P$4:$P$103,MATCH(ROWS($E$5:E5),VALORIZACIÓN!$S$4:$S$103,0))) -> 1950 | K5: =VALORIZACIÓN!P4 -> 1950
A6: Valorizado acumulado | B6: =SUM(VALORIZACIÓN!O4:O103) -> 35839 | E6: =IFERROR(INDEX(VALORIZACIÓN!$B$4:$B$103,MATCH(ROWS($E$5:E6),VALORIZACIÓN!$S$4:$S$103,0)),"") -> ARQ-02 | F6: =IFERROR(INDEX(VALORIZACIÓN!$C$4:$C$103,MATCH(ROWS($E$5:E6),VALORIZACIÓN!$S$4:$S$103,0)),"") -> Tabiquería drywall | G6: =IF(E6="","",INDEX(VALORIZACIÓN!$N$4:$N$103,MATCH(ROWS($E$5:E6),VALORIZACIÓN!$S$4:$S$103,0))) -> 3420 | H6: =IF(E6="","",INDEX(VALORIZACIÓN!$J$4:$J$103,MATCH(ROWS($E$5:E6),VALORIZACIÓN!$S$4:$S$103,0))) -> 0.3 | I6: =IF(E6="","",INDEX(VALORIZACIÓN!$O$4:$O$103,MATCH(ROWS($E$5:E6),VALORIZACIÓN!$S$4:$S$103,0))) -> 5130 | J6: =IF(E6="","",INDEX(VALORIZACIÓN!$P$4:$P$103,MATCH(ROWS($E$5:E6),VALORIZACIÓN!$S$4:$S$103,0))) -> 11970 | K6: =VALORIZACIÓN!P5 -> 11970
A7: Adicionales aprobados | B7: =SUMIFS(ADICIONALES!I4:I103,ADICIONALES!C4:C103,"Adicional",ADICIONALES!J4:J103,"Aprobado") -> 3200 | E7: =IFERROR(INDEX(VALORIZACIÓN!$B$4:$B$103,MATCH(ROWS($E$5:E7),VALORIZACIÓN!$S$4:$S$103,0)),"") -> ARQ-03 | F7: =IFERROR(INDEX(VALORIZACIÓN!$C$4:$C$103,MATCH(ROWS($E$5:E7),VALORIZACIÓN!$S$4:$S$103,0)),"") -> Cielorraso | G7: =IF(E7="","",INDEX(VALORIZACIÓN!$N$4:$N$103,MATCH(ROWS($E$5:E7),VALORIZACIÓN!$S$4:$S$103,0))) -> 1116 | H7: =IF(E7="","",INDEX(VALORIZACIÓN!$J$4:$J$103,MATCH(ROWS($E$5:E7),VALORIZACIÓN!$S$4:$S$103,0))) -> 0.1 | I7: =IF(E7="","",INDEX(VALORIZACIÓN!$O$4:$O$103,MATCH(ROWS($E$5:E7),VALORIZACIÓN!$S$4:$S$103,0))) -> 1116 | J7: =IF(E7="","",INDEX(VALORIZACIÓN!$P$4:$P$103,MATCH(ROWS($E$5:E7),VALORIZACIÓN!$S$4:$S$103,0))) -> 10044 | K7: =VALORIZACIÓN!P6 -> 10044
A8: Deductivos aprobados | B8: =SUMIFS(ADICIONALES!I4:I103,ADICIONALES!C4:C103,"Deductivo",ADICIONALES!J4:J103,"Aprobado") -> 1140 | E8: =IFERROR(INDEX(VALORIZACIÓN!$B$4:$B$103,MATCH(ROWS($E$5:E8),VALORIZACIÓN!$S$4:$S$103,0)),"") -> ARQ-04 | F8: =IFERROR(INDEX(VALORIZACIÓN!$C$4:$C$103,MATCH(ROWS($E$5:E8),VALORIZACIÓN!$S$4:$S$103,0)),"") -> Piso porcelanato | G8: =IF(E8="","",INDEX(VALORIZACIÓN!$N$4:$N$103,MATCH(ROWS($E$5:E8),VALORIZACIÓN!$S$4:$S$103,0))) -> 3894 | H8: =IF(E8="","",INDEX(VALORIZACIÓN!$J$4:$J$103,MATCH(ROWS($E$5:E8),VALORIZACIÓN!$S$4:$S$103,0))) -> 0.3 | I8: =IF(E8="","",INDEX(VALORIZACIÓN!$O$4:$O$103,MATCH(ROWS($E$5:E8),VALORIZACIÓN!$S$4:$S$103,0))) -> 7788 | J8: =IF(E8="","",INDEX(VALORIZACIÓN!$P$4:$P$103,MATCH(ROWS($E$5:E8),VALORIZACIÓN!$S$4:$S$103,0))) -> 18172 | K8: =VALORIZACIÓN!P7 -> 18172
A9: Contrato actualizado | B9: =B4+B7-B8 -> 134560 | E9: =IFERROR(INDEX(VALORIZACIÓN!$B$4:$B$103,MATCH(ROWS($E$5:E9),VALORIZACIÓN!$S$4:$S$103,0)),"") -> ARQ-05 | F9: =IFERROR(INDEX(VALORIZACIÓN!$C$4:$C$103,MATCH(ROWS($E$5:E9),VALORIZACIÓN!$S$4:$S$103,0)),"") -> Pintura general | G9: =IF(E9="","",INDEX(VALORIZACIÓN!$N$4:$N$103,MATCH(ROWS($E$5:E9),VALORIZACIÓN!$S$4:$S$103,0))) -> 4080 | H9: =IF(E9="","",INDEX(VALORIZACIÓN!$J$4:$J$103,MATCH(ROWS($E$5:E9),VALORIZACIÓN!$S$4:$S$103,0))) -> 0.3 | I9: =IF(E9="","",INDEX(VALORIZACIÓN!$O$4:$O$103,MATCH(ROWS($E$5:E9),VALORIZACIÓN!$S$4:$S$103,0))) -> 4080 | J9: =IF(E9="","",INDEX(VALORIZACIÓN!$P$4:$P$103,MATCH(ROWS($E$5:E9),VALORIZACIÓN!$S$4:$S$103,0))) -> 9520 | K9: =VALORIZACIÓN!P8 -> 9520
A10: Pagado acumulado | B10: =SUM('CONTROL DE PAGOS'!H4:H53) -> 23530 | E10: =IFERROR(INDEX(VALORIZACIÓN!$B$4:$B$103,MATCH(ROWS($E$5:E10),VALORIZACIÓN!$S$4:$S$103,0)),"") -> ELE-01 | F10: =IFERROR(INDEX(VALORIZACIÓN!$C$4:$C$103,MATCH(ROWS($E$5:E10),VALORIZACIÓN!$S$4:$S$103,0)),"") -> Red eléctrica | G10: =IF(E10="","",INDEX(VALORIZACIÓN!$N$4:$N$103,MATCH(ROWS($E$5:E10),VALORIZACIÓN!$S$4:$S$103,0))) -> 2775 | H10: =IF(E10="","",INDEX(VALORIZACIÓN!$J$4:$J$103,MATCH(ROWS($E$5:E10),VALORIZACIÓN!$S$4:$S$103,0))) -> 0.4 | I10: =IF(E10="","",INDEX(VALORIZACIÓN!$O$4:$O$103,MATCH(ROWS($E$5:E10),VALORIZACIÓN!$S$4:$S$103,0))) -> 7400 | J10: =IF(E10="","",INDEX(VALORIZACIÓN!$P$4:$P$103,MATCH(ROWS($E$5:E10),VALORIZACIÓN!$S$4:$S$103,0))) -> 11100 | K10: =VALORIZACIÓN!P9 -> 11100
A11: Saldo por pagar | B11: =B6-B10 -> 12309 | E11: =IFERROR(INDEX(VALORIZACIÓN!$B$4:$B$103,MATCH(ROWS($E$5:E11),VALORIZACIÓN!$S$4:$S$103,0)),"") -> SAN-01 | F11: =IFERROR(INDEX(VALORIZACIÓN!$C$4:$C$103,MATCH(ROWS($E$5:E11),VALORIZACIÓN!$S$4:$S$103,0)),"") -> Adecuación sanitaria | G11: =IF(E11="","",INDEX(VALORIZACIÓN!$N$4:$N$103,MATCH(ROWS($E$5:E11),VALORIZACIÓN!$S$4:$S$103,0))) -> 1840 | H11: =IF(E11="","",INDEX(VALORIZACIÓN!$J$4:$J$103,MATCH(ROWS($E$5:E11),VALORIZACIÓN!$S$4:$S$103,0))) -> 0.2 | I11: =IF(E11="","",INDEX(VALORIZACIÓN!$O$4:$O$103,MATCH(ROWS($E$5:E11),VALORIZACIÓN!$S$4:$S$103,0))) -> 1840 | J11: =IF(E11="","",INDEX(VALORIZACIÓN!$P$4:$P$103,MATCH(ROWS($E$5:E11),VALORIZACIÓN!$S$4:$S$103,0))) -> 7360 | K11: =VALORIZACIÓN!P10 -> 7360
A12: Saldo por ejecutar | B12: =B9-B6 -> 98721 | E12: =IFERROR(INDEX(VALORIZACIÓN!$B$4:$B$103,MATCH(ROWS($E$5:E12),VALORIZACIÓN!$S$4:$S$103,0)),"") -> MOB-01 | F12: =IFERROR(INDEX(VALORIZACIÓN!$C$4:$C$103,MATCH(ROWS($E$5:E12),VALORIZACIÓN!$S$4:$S$103,0)),"") -> Carpintería fija | G12: =IF(E12="","",INDEX(VALORIZACIÓN!$N$4:$N$103,MATCH(ROWS($E$5:E12),VALORIZACIÓN!$S$4:$S$103,0))) -> 740 | H12: =IF(E12="","",INDEX(VALORIZACIÓN!$J$4:$J$103,MATCH(ROWS($E$5:E12),VALORIZACIÓN!$S$4:$S$103,0))) -> 0.15 | I12: =IF(E12="","",INDEX(VALORIZACIÓN!$O$4:$O$103,MATCH(ROWS($E$5:E12),VALORIZACIÓN!$S$4:$S$103,0))) -> 2220 | J12: =IF(E12="","",INDEX(VALORIZACIÓN!$P$4:$P$103,MATCH(ROWS($E$5:E12),VALORIZACIÓN!$S$4:$S$103,0))) -> 12580 | K12: =VALORIZACIÓN!P11 -> 12580
A13: % avance económico acumulado | B13: =IFERROR(B6/B9,0) -> 0.26634215 | E13: =IFERROR(INDEX(VALORIZACIÓN!$B$4:$B$103,MATCH(ROWS($E$5:E13),VALORIZACIÓN!$S$4:$S$103,0)),"") -> VID-01 | F13: =IFERROR(INDEX(VALORIZACIÓN!$C$4:$C$103,MATCH(ROWS($E$5:E13),VALORIZACIÓN!$S$4:$S$103,0)),"") -> Mamparas y vidrio | G13: =IF(E13="","",INDEX(VALORIZACIÓN!$N$4:$N$103,MATCH(ROWS($E$5:E13),VALORIZACIÓN!$S$4:$S$103,0))) -> 4095 | H13: =IF(E13="","",INDEX(VALORIZACIÓN!$J$4:$J$103,MATCH(ROWS($E$5:E13),VALORIZACIÓN!$S$4:$S$103,0))) -> 0.25 | I13: =IF(E13="","",INDEX(VALORIZACIÓN!$O$4:$O$103,MATCH(ROWS($E$5:E13),VALORIZACIÓN!$S$4:$S$103,0))) -> 4095 | J13: =IF(E13="","",INDEX(VALORIZACIÓN!$P$4:$P$103,MATCH(ROWS($E$5:E13),VALORIZACIÓN!$S$4:$S$103,0))) -> 12285 | K13: =VALORIZACIÓN!P12 -> 12285
E14: =IFERROR(INDEX(VALORIZACIÓN!$B$4:$B$103,MATCH(ROWS($E$5:E14),VALORIZACIÓN!$S$4:$S$103,0)),"") -> FIN-01 | F14: =IFERROR(INDEX(VALORIZACIÓN!$C$4:$C$103,MATCH(ROWS($E$5:E14),VALORIZACIÓN!$S$4:$S$103,0)),"") -> Limpieza y cierre | G14: =IF(E14="","",INDEX(VALORIZACIÓN!$N$4:$N$103,MATCH(ROWS($E$5:E14),VALORIZACIÓN!$S$4:$S$103,0))) -> 1120 | H14: =IF(E14="","",INDEX(VALORIZACIÓN!$J$4:$J$103,MATCH(ROWS($E$5:E14),VALORIZACIÓN!$S$4:$S$103,0))) -> 0.4 | I14: =IF(E14="","",INDEX(VALORIZACIÓN!$O$4:$O$103,MATCH(ROWS($E$5:E14),VALORIZACIÓN!$S$4:$S$103,0))) -> 1120 | J14: =IF(E14="","",INDEX(VALORIZACIÓN!$P$4:$P$103,MATCH(ROWS($E$5:E14),VALORIZACIÓN!$S$4:$S$103,0))) -> 1680 | K14: =VALORIZACIÓN!P13 -> 1680
A16: Composición del contrato | E16: Progreso
A17: Contrato base | B17: =B4 -> 132500 | E17: Avance económico | F17: =B13 -> 0.26634215
A18: Adicionales | B18: =B7 -> 3200 | E18: Pendiente | F18: =1-F17 -> 0.73365785
A19: Deductivos | B19: =B8 -> 1140

Sheet PRESENTACIÓN
A1: VALORIZACIÓN DE AVANCE DE OBRA
A3: Cliente | B3: ='DATOS GENERALES'!B3 -> Cliente ejemplo SAC | D3: Contrato base | F3: Valorizado período | H3: Valorizado acumulado | J3: Elaborado por | K3: ________________________
A4: Proyecto | B4: ='DATOS GENERALES'!B4 -> Remodelación Oficinas Piso 3 | D4: =RESUMEN!B4 -> 132500 | F4: =RESUMEN!B5 -> 23530 | H4: =RESUMEN!B6 -> 35839
A5: Código | B5: ='DATOS GENERALES'!B5 -> VAL-001 | J5: Revisado por | K5: ________________________
A6: N.° valorización | B6: ='DATOS GENERALES'!B12 -> 1 | D6: Adicionales netos | F6: Saldo por ejecutar | H6: Saldo por pagar
A7: Periodo | B7: ='DATOS GENERALES'!B13 -> Mes 1 | D7: =RESUMEN!B7-RESUMEN!B8 -> 2060 | F7: =RESUMEN!B12 -> 98721 | H7: =RESUMEN!B11 -> 12309 | J7: Aprobado por | K7: ________________________
A8: Fecha de corte | B8: ='DATOS GENERALES'!B14 -> 2026-03-16
A9: Estado | B9: ='DATOS GENERALES'!B18 -> Borrador
A11: Resumen económico | F11: Partidas valorizadas del período
A12: Monto contratado | B12: =RESUMEN!B4 -> 132500 | F12: Código | G12: Partida | H12: Monto contratado | I12: Avance período % | J12: Valorizado período | K12: Saldo
A13: Adicionales | B13: =RESUMEN!B7 -> 3200 | F13: =RESUMEN!E5 -> ARQ-01 | G13: =RESUMEN!F5 -> Demoliciones menores | H13: =RESUMEN!G5 -> 450 | I13: =RESUMEN!H5 -> 0.35 | J13: =RESUMEN!J5 -> 1950 | K13: =RESUMEN!K5 -> 1950
A14: Deductivos | B14: =RESUMEN!B8 -> 1140 | F14: =RESUMEN!E6 -> ARQ-02 | G14: =RESUMEN!F6 -> Tabiquería drywall | H14: =RESUMEN!G6 -> 3420 | I14: =RESUMEN!H6 -> 0.3 | J14: =RESUMEN!J6 -> 11970 | K14: =RESUMEN!K6 -> 11970
A15: Contrato actualizado | B15: =RESUMEN!B9 -> 134560 | F15: =RESUMEN!E7 -> ARQ-03 | G15: =RESUMEN!F7 -> Cielorraso | H15: =RESUMEN!G7 -> 1116 | I15: =RESUMEN!H7 -> 0.1 | J15: =RESUMEN!J7 -> 10044 | K15: =RESUMEN!K7 -> 10044
A16: Valorizado del período | B16: =RESUMEN!B5 -> 23530 | F16: =RESUMEN!E8 -> ARQ-04 | G16: =RESUMEN!F8 -> Piso porcelanato | H16: =RESUMEN!G8 -> 3894 | I16: =RESUMEN!H8 -> 0.3 | J16: =RESUMEN!J8 -> 18172 | K16: =RESUMEN!K8 -> 18172
A17: Valorizado acumulado | B17: =RESUMEN!B6 -> 35839 | F17: =RESUMEN!E9 -> ARQ-05 | G17: =RESUMEN!F9 -> Pintura general | H17: =RESUMEN!G9 -> 4080 | I17: =RESUMEN!H9 -> 0.3 | J17: =RESUMEN!J9 -> 9520 | K17: =RESUMEN!K9 -> 9520
A18: Pagado acumulado | B18: =RESUMEN!B10 -> 23530 | F18: =RESUMEN!E10 -> ELE-01 | G18: =RESUMEN!F10 -> Red eléctrica | H18: =RESUMEN!G10 -> 2775 | I18: =RESUMEN!H10 -> 0.4 | J18: =RESUMEN!J10 -> 11100 | K18: =RESUMEN!K10 -> 11100
A19: Saldo por pagar | B19: =RESUMEN!B11 -> 12309 | F19: =RESUMEN!E11 -> SAN-01 | G19: =RESUMEN!F11 -> Adecuación sanitaria | H19: =RESUMEN!G11 -> 1840 | I19: =RESUMEN!H11 -> 0.2 | J19: =RESUMEN!J11 -> 7360 | K19: =RESUMEN!K11 -> 7360
A20: Saldo por ejecutar | B20: =RESUMEN!B12 -> 98721 | F20: =RESUMEN!E12 -> MOB-01 | G20: =RESUMEN!F12 -> Carpintería fija | H20: =RESUMEN!G12 -> 740 | I20: =RESUMEN!H12 -> 0.15 | J20: =RESUMEN!J12 -> 12580 | K20: =RESUMEN!K12 -> 12580
A21: % avance económico | B21: =RESUMEN!B13 -> 0.26634215 | F21: =RESUMEN!E13 -> VID-01 | G21: =RESUMEN!F13 -> Mamparas y vidrio | H21: =RESUMEN!G13 -> 4095 | I21: =RESUMEN!H13 -> 0.25 | J21: =RESUMEN!J13 -> 12285 | K21: =RESUMEN!K13 -> 12285
F22: =RESUMEN!E14 -> FIN-01 | G22: =RESUMEN!F14 -> Limpieza y cierre | H22: =RESUMEN!G14 -> 1120 | I22: =RESUMEN!H14 -> 0.4 | J22: =RESUMEN!J14 -> 1680 | K22: =RESUMEN!K14 -> 1680
A23: Progreso económico
A24: Avance acumulado | B24: =RESUMEN!B13 -> 0.26634215
A25: Pendiente | B25: =1-B24 -> 0.73365785
